django_gm2m-1.3.dist-info/licenses/LICENSE.txt
gm2m/__init__.py
gm2m/apps.py
gm2m/contenttypes.py
gm2m/deletion.py
gm2m/descriptors.py
gm2m/fields.py
gm2m/helpers.py
gm2m/managers.py
gm2m/models.py
gm2m/monkeypatch.py
gm2m/query.py
gm2m/relations.py
gm2m/signals.py
gm2m/version.py
gm2m/serializers/__init__.py
gm2m/serializers/json.py
gm2m/serializers/python.py
gm2m/serializers/pyyaml.py
gm2m/serializers/xml_serializer.py
django_gm2m-1.3.dist-info/METADATA
django_gm2m-1.3.dist-info/WHEEL
django_gm2m-1.3.dist-info/top_level.txt
django_gm2m-1.3.dist-info/zip-safe
django_gm2m-1.3.dist-info/RECORD
