Metadata-Version: 2.4
Name: django-gm2m
Version: 1.3
Summary: Django generic many-to-many field
Home-page: https://github.com/tkhyn/django-gm2m
Author: Thomas Khyn
Author-email: thomas@ksytek.com
Keywords: django,generic,many-to-many
Classifier: Programming Language :: Python
Classifier: Programming Language :: Python :: 3
Classifier: License :: OSI Approved :: MIT License
Classifier: Operating System :: OS Independent
Classifier: Development Status :: 5 - Production/Stable
Classifier: Framework :: Django
Classifier: Environment :: Other Environment
License-File: LICENSE.txt
Requires-Dist: Django>=2.2
Dynamic: author
Dynamic: author-email
Dynamic: classifier
Dynamic: description
Dynamic: home-page
Dynamic: keywords
Dynamic: license-file
Dynamic: requires-dist
Dynamic: summary
